later/__init__.py
later/coroutine.py
later/event.py
later/py.typed
later/task.py
later/tests/__init__.py
later/tests/base.py
later/tests/test_coroutine.py
later/tests/test_event.py
later/tests/test_task.py
later/tests/test_version.py
later/tests/unittest/test_case.py
later/tests/unittest/test_mock.py
later/unittest/__init__.py
later/unittest/case.py
later/unittest/mock.py
later/unittest/test_task.py
later-25.8.1.dist-info/licenses/LICENSE
later-25.8.1.dist-info/WHEEL
later-25.8.1.dist-info/METADATA
later-25.8.1.dist-info/RECORD
