Metadata-Version: 2.4
Name: later
Version: 25.8.1
Summary: A toolbox for asyncio services
Keywords: asyncio,later
Author: Meta Platforms, Inc
Author-email: Jason Fried <fried@meta.com>
Requires-Python: >=3.10
Classifier: Development Status :: 5 - Production/Stable
Classifier: Framework :: AsyncIO
Classifier: Intended Audience :: Developers
Classifier: License :: OSI Approved :: Apache Software License
Classifier: License :: OSI Approved :: Apache Software License
Classifier: Operating System :: POSIX
Classifier: Operating System :: MacOS :: MacOS X
Classifier: Topic :: Software Development :: Libraries :: Python Modules
Classifier: Topic :: Software Development :: Testing
License-File: LICENSE
Requires-Dist: async-timeout >= 2.0.0, <= 5.0.1
Requires-Dist: async-timeout==5.0.1 ; extra == "dev"
Requires-Dist: coverage==7.10.5 ; extra == "dev"
Requires-Dist: flit==3.12.0 ; extra == "dev"
Project-URL: Github, https://github.com/facebookincubator/later
Provides-Extra: dev
